redis_rate_limit/__init__.py
python_redis_rate_limit-0.0.8.dist-info/LICENSE
python_redis_rate_limit-0.0.8.dist-info/METADATA
python_redis_rate_limit-0.0.8.dist-info/WHEEL
python_redis_rate_limit-0.0.8.dist-info/top_level.txt
python_redis_rate_limit-0.0.8.dist-info/RECORD
