Metadata-Version: 2.1
Name: python-redis-rate-limit
Version: 0.0.8
Summary: Python Rate Limiter based on Redis.
Home-page: https://github.com/evoluxbr/python-redis-rate-limit
Author: Victor Torres
Author-email: vpaivatorres@gmail.com
License: MIT
Platform: UNKNOWN
Classifier: Development Status :: 4 - Beta
Classifier: Intended Audience :: Developers
Classifier: Programming Language :: Python
Classifier: Programming Language :: Python :: 2.7
Classifier: Programming Language :: Python :: 3.5
Classifier: Programming Language :: Python :: 3.6
Classifier: License :: OSI Approved :: MIT License
License-File: LICENSE
Requires-Dist: redis
